[
  {
    "name": null,
    "methods": [
      "HEAD",
      "GET"
    ],
    "paramNames": [],
    "path": "/",
    "regexp": "/^(?:\\/(?=$))?$/",
    "stack": [
      "wrappedController"
    ]
  },
  {
    "name": null,
    "methods": [
      "POST"
    ],
    "paramNames": [],
    "path": "/api/auth/login",
    "regexp": "/^\\/api\\/auth\\/login(?:\\/(?=$))?$/",
    "stack": [
      "wrappedController"
    ]
  },
  {
    "name": null,
    "methods": [
      "POST"
    ],
    "paramNames": [],
    "path": "/api/auth/register",
    "regexp": "/^\\/api\\/auth\\/register(?:\\/(?=$))?$/",
    "stack": [
      "wrappedController"
    ]
  },
  {
    "name": null,
    "methods": [
      "HEAD",
      "GET"
    ],
    "paramNames": [],
    "path": "/api/dashboard/stats",
    "regexp": "/^\\/api\\/dashboard\\/stats(?:\\/(?=$))?$/",
    "stack": [
      "wrappedController"
    ]
  },
  {
    "name": null,
    "methods": [
      "HEAD",
      "GET"
    ],
    "paramNames": [],
    "path": "/api/dashboard/trends",
    "regexp": "/^\\/api\\/dashboard\\/trends(?:\\/(?=$))?$/",
    "stack": [
      "wrappedController"
    ]
  }
]